[
    {
        "category": "DogTreat",
        "name": "Premios_gourmet",
        "price": 49.99,
        "quantity": 10,
        "imgUrl": "https://i.imgur.com/Yn8K3SG.jpeg",
        "description": "Premios gourmet para el más querido de la familia."
    },
    {
        "category": "DogTreat",
        "name": "Premios_de_calabaza",
        "price": 39.99,
        "quantity": 10,
        "imgUrl": "https://i.imgur.com/7OFeqcF.jpeg",
        "description": "Premios de calabaza para aquellos con gustos distintos."
    },
    {
        "category": "DogTreat",
        "name": "Premios_de_fresa",
        "price": 44.99,
        "quantity": 10,
        "imgUrl": "https://i.imgur.com/yA78DoP.jpeg",
        "description": "Premios de fresa para los seres distinguidos."
    },
    {
        "category": "DogTreat",
        "name": "Premios_de_mango",
        "price": 44.99,
        "quantity": 10,
        "imgUrl": "https://i.imgur.com/rZG0Kt7.jpeg",
        "description": "Premios de mango para los más dulces."
    },
    {
        "category": "DogTreat",
        "name": "Premios_de_chocolate",
        "price": 39.99,
        "quantity": 10,
        "imgUrl": "https://i.imgur.com/tMw05Zl.png",
        "description": "Chocolate seguro para el perro, que no se pierda la oportunidad."
    },
    {
        "category": "DogTreat",
        "name": "Premios_de_variedad",
        "price": 24.99,
        "quantity": 10,
        "imgUrl": "",
        "description": "Variedad de premios para que no se quede con ganas de más."
    },
    {
        "category": "DogTreat",
        "name": "Premios_de_carne-seca",
        "price": 54.99,
        "quantity": 10,
        "imgUrl": "https://i.imgur.com/GwM50D4.png",
        "description": "Carne seca para el consentido de la casa."
    },
    {
        "category": "DogTreat",
        "name": "Premios_de_pollo-deshidratado",
        "price": 54.99,
        "quantity": 10,
        "imgUrl": "https://i.imgur.com/m3apg0M.jpeg",
        "description": "Pollo deshidratado, el preferido para el niño."
    },
	{
        "category": "DogBed",
        "name": "Cama-anti-estres",
        "price": 859.69,
        "quantity": 10,
        "imgUrl": "https://vicvaporuh.github.io/VL_Pract1_PW.github.io/CamaAntiEstres.png",
        "description": "Cama anti estres para el mas chambeador de la casa. "
    },
	{
        "category": "DogBed",
        "name": "Cama-calientita",
        "price": 580,
        "quantity": 10,
        "imgUrl": "https://vicvaporuh.github.io/VL_Pract1_PW.github.io/CamaCalientita.png",
        "description": "La cria es friolenta, esta cama calientita es para ti. "
    },
	{
        "category": "DogBed",
        "name": "Cama-cuadrada",
        "price": 999.99,
        "quantity": 10,
        "imgUrl": "https://vicvaporuh.github.io/VL_Pract1_PW.github.io/CamaCuadradaPerro.jpg",
        "description": "Diseñada para los lobos defensores. "
    },
	{
        "category": "DogBed",
        "name": "Cama-ecologica",
        "price": 799.99,
        "quantity": 10,
        "imgUrl": "https://vicvaporuh.github.io/VL_Pract1_PW.github.io/CamaEcologicaPerro.jpeg",
        "description": "Cuidando al medio ambiente, y a la bendicion con esta cama ecologica. "
    },
	{
        "category": "DogBed",
        "name": "Cama-elevada",
        "price": 999.99,
        "quantity": 10,
        "imgUrl": "https://vicvaporuh.github.io/VL_Pract1_PW.github.io/CamaElevada.png",
        "description": " Cama elevada para aquellos haters del piso. "
    },
	{
        "category": "DogBed",
        "name": "Cama-doble",
        "price": 1800.00,
        "quantity": 10,
        "imgUrl": "https://vicvaporuh.github.io/VL_Pract1_PW.github.io/CamaPerroHumano.jpg",
        "description": "Por si el niño le tiene miedo a dormir solo esta cama doble es para ti."
    },
	{
        "category": "DogBed",
        "name": "Cama-sillon",
        "price": 1350.00,
        "quantity": 10,
        "imgUrl": "https://vicvaporuh.github.io/VL_Pract1_PW.github.io/SillonPerro.jpg",
        "description": "Tu perro quiere incluirse a la reunion, esta es la solucion. "
    },
	{
        "category": "DogBed",
        "name": "Cama-sillon-deluxe",
        "price": 4999.99,
        "quantity": 10,
        "imgUrl": "https://vicvaporuh.github.io/VL_Pract1_PW.github.io/SillonPerroDeluxe.png",
        "description": "Para los perros mas finos del condado, un sillon deluxe."
    }
]

